pipedata/__init__.py
pipedata/core/__init__.py
pipedata/core/chain.py
pipedata/core/links.py
pipedata/core/ops.py
pipedata/core/stream.py
pipedata/ops/__init__.py
pipedata/ops/files.py
pipedata/ops/records.py
pipedata/ops/storage.py
pipedata/py.typed
pipedata-0.4.dist-info/LICENSE
pipedata-0.4.dist-info/METADATA
pipedata-0.4.dist-info/WHEEL
pipedata-0.4.dist-info/RECORD
